{
  "id": "materia-chargen-dnd5e",
  "title": "Materia D&D 5.M Character Generator",
  "description": "Character generator application for the Materia D&D 5.M system.",
  "version": "#{VERSION}#",
  "library": "false",
  "manifestPlusVersion": "1.2.0",
  "compatibility": {
    "minimum": 10,
    "verified": 10,
    "maximum": 11
  },
  "authors": [
    {
      "name": "ddipaolo",
      "url": "https://github.com/ddipaolo",
      "discord": "diddlypow#5059"
    }
  ],
  "relationships": {
    "systems": [],
    "requires": []
  },
  "esmodules": [
    "scripts/module.js"
  ],
  "scripts": [
    "scripts/lib/lib.js"
  ],
  "styles": [
    "styles/module.css"
  ],
  "languages": [
    {
      "lang": "en",
      "name": "English",
      "path": "languages/en.json"
    }
  ],
  "url": "#{URL}#",
  "manifest": "#{MANIFEST}#",
  "download": "#{DOWNLOAD}#",
  "license": "LICENSE",
  "readme": "README.md"
}
